[{"Origin":"hà nội","Instances":["hn","hnoi","hanoi"]},{"Origin":"sài gòn","Instances":["sgon","sg","saigon"]},{"Origin":"hồ chí minh","Instances":["hcm","tphcm"]},{"Origin":"ủy ban nhân dân","Instances":["ubnd"]},{"Origin":"chương trình khuyến mãi","Instances":["ctkm"]},{"Origin":"giao hàng tiết kiệm","Instances":["ghtk"]},{"Origin":"không","Instances":["hok","khong","kô","hk","khg","ko"]},{"Origin":"được","Instances":["đươc","đuọc","dc","đx","dx","đuoc","đc"]},{"Origin":"bao nhiêu","Instances":["bnhiue","bn","bnh","bnju","bnhieeu","bnhii","bnhiu","bnhiêu","bnhjeu","bnhieu","bnhju"]},{"Origin":"chuyển khoản","Instances":["ckhoan","ck","chk"]},{"Origin":"với","Instances":["vơid","voeis","vơis","vs","vz","vơia","zoi","zới","vois"]},{"Origin":"à","Instances":["àh","ak","ah","àk","ák"]},{"Origin":"ạ","Instances":["ạh"]},{"Origin":"trước","Instances":["trk","truóc","trươcs","trc","trươc","truoc"]},{"Origin":"hôm trước","Instances":["htrc","htruoc"]},{"Origin":"gì","Instances":["zì","j"]},{"Origin":"như thế nào","Instances":["ntnao","ntn"]},{"Origin":"như thế này","Instances":["ntnay"]},{"Origin":"thế nào","Instances":["thenao","tn","tnao","thnao"]},{"Origin":"ừ","Instances":["uhh","umh","uk","uki","ukie","uhm","uh","ukm","uke"]},{"Origin":"tài khoản","Instances":["tkhoan","tk"]},{"Origin":"số tài khoản","Instances":["stk"]},{"Origin":"sản phẩm","Instances":["sp","spham"]},{"Origin":"người","Instances":["ng","nguoi"]},{"Origin":"số điện thoại","Instances":["sđt","sdt"]},{"Origin":"hôm nay","Instances":["hnay"]},{"Origin":"hôm nữa","Instances":["hnua"]},{"Origin":"hôm nào","Instances":["hnao"]},{"Origin":"luôn","Instances":["luô","lun","luon"]},{"Origin":"thành phố","Instances":["tp"]},{"Origin":"mình","Instances":["mibhf","mfinh","mính","mùnh","mk","mìmh","mjh","mjk","minhd","mik","mimh","minhf","mimhf","minhg","mh","mìnk","mìh","midnh"]},{"Origin":"nhắn tin","Instances":["nt"]},{"Origin":"vậy","Instances":["zậy","zay","zj","zi","zị","zạy","z"]},{"Origin":"phải","Instances":["fai","fải"]},{"Origin":"kiểm tra","Instances":["ktra","ktr"]},{"Origin":"nhé","Instances":["nhed","nhes"]},{"Origin":"bây giờ","Instances":["bjo","bgio"]},{"Origin":"hôm qua","Instances":["hqua","hqa"]},{"Origin":"đang","Instances":["đag","đnag"]},{"Origin":"có","Instances":["cos","coa"]},{"Origin":"nhé","Instances":["nhed","nhea","nhez"]},{"Origin":"ơi","Instances":["oiw","oei","oqi","oie","oiq","oii"]},{"Origin":"nhưng","Instances":["nhg","nhug","nhưg"]},{"Origin":"trả lời","Instances":["tl","trloi","trl","tloi"]},{"Origin":"sử dụng","Instances":["sd"]},{"Origin":"giờ","Instances":["gjo","jo"]},{"Origin":"sản xuất","Instances":["sx"]},{"Origin":"hàng","Instances":["hàg"]},{"Origin":"vâng","Instances":["vâg"]},{"Origin":"qua","Instances":["wa"]},{"Origin":"thích","Instances":["thjk","thik","thich","thic","thick"]},{"Origin":"xong","Instances":["xog","xogn"]},{"Origin":"người ta","Instances":["ngta","nta"]},{"Origin":"quá","Instances":["qá"]},{"Origin":"khuyến mãi","Instances":["kmai","km"]},{"Origin":"tiền","Instances":["xiền"]},{"Origin":"rồi","Instances":["roiif"]},{"Origin":"phần mềm","Instances":["pm"]},{"Origin":"hóa đơn đt","Instances":["hđđt","hddt"]},{"Origin":"công ty","Instances":["cty"]},{"Origin":"tài sản cố định","Instances":["tscd","tscđ"]},{"Origin":"mã số thuế","Instances":["mst"]},{"Origin":"nhà cung cấp","Instances":["ncc"]},{"Origin":"dữ liệu","Instances":["dl"]},{"Origin":"nguyên vật liệu","Instances":["nvl"]},{"Origin":"anh chị","Instances":["ac"]},{"Origin":"báo cáo tài chính","Instances":["bctc"]},{"Origin":"cơ quan thuế","Instances":["cqt"]},{"Origin":"phương pháp","Instances":["pp"]},{"Origin":"kiểm tra","Instances":["ktra"]},{"Origin":"phần mềm kế toán","Instances":["pmkt"]},{"Origin":"chiết khấu thương mại","Instances":["cktm"]},{"Origin":"chứng từ","Instances":["ctu","ct"]},{"Origin":"sản xuất","Instances":["sx"]},{"Origin":"vật tư hàng hóa","Instances":["vthh"]},{"Origin":"báo cáo","Instances":["bc"]},{"Origin":"ủy nhiệm chi","Instances":["unc"]},{"Origin":"nghiệp vụ khác","Instances":["nvk"]},{"Origin":"hạch toán","Instances":["ht"]},{"Origin":"tài sản","Instances":["ts"]},{"Origin":"phiếu xuất kho","Instances":["pxk"]},{"Origin":"quan hệ ngân sách","Instances":["qhns"]},{"Origin":"bình thường","Instances":["bt"]},{"Origin":"thu nhập doanh nghiệp","Instances":["tndn"]},{"Origin":"làm","Instances":["lm"]},{"Origin":"tập hợp chi phí","Instances":["thcp"]},{"Origin":"hóa đơn","Instances":["hdon"]},{"Origin":"thông báo sai sót","Instances":["tbss"]},{"Origin":"thu nhập cá nhân","Instances":["tncn"]},{"Origin":"hướng dẫn","Instances":["hdan"]},{"Origin":"nhập khẩu","Instances":["nk"]},{"Origin":"phát sinh","Instances":["psinh"]},{"Origin":"chứng từ bán hàng","Instances":["ctbh"]},{"Origin":"chi phí mua hàng","Instances":["cpmh"]},{"Origin":"giờ","Instances":["jo"]},{"Origin":"hộ kinh doanh","Instances":["hkd"]},{"Origin":"hàng hóa dịch vụ","Instances":["hhdv"]},{"Origin":"dịch vụ","Instances":["dv"]},{"Origin":"thông báo","Instances":["tbao"]},{"Origin":"công cụ dụng cụ","Instances":["ccdc"]},{"Origin":"chi phí trả trước","Instances":["cptt"]},{"Origin":"có","Instances":["cso"]},{"Origin":"kế toán","Instances":["ktoan","ketoan"]},{"Origin":"kế toán trưởng","Instances":["ktt"]},{"Origin":"phân bổ","Instances":["pb"]},{"Origin":"khoản mục chi phí","Instances":["kmcp"]}]